{
  "annotations": {
    "list": [
      {
        "builtIn": 1,
        "datasource": {
          "type": "grafana",
          "uid": "-- Grafana --"
        },
        "enable": true,
        "hide": true,
        "iconColor": "rgba(0, 211, 255, 1)",
        "name": "Annotations & Alerts",
        "target": {
          "limit": 100,
          "matchAny": false,
          "tags": [],
          "type": "dashboard"
        },
        "type": "dashboard"
      }
    ]
  },
  "editable": true,
  "fiscalYearStartMonth": 0,
  "graphTooltip": 0,
  "id": 98,
  "links": [],
  "liveNow": false,
  "panels": [
    {
      "datasource": {
        "type": "prometheus",
        "uid": "${DATASOURCE}"
      },
      "fieldConfig": {
        "defaults": {
          "color": {
            "mode": "palette-classic"
          },
          "custom": {
            "axisLabel": "",
            "axisPlacement": "auto",
            "barAlignment": 0,
            "drawStyle": "line",
            "fillOpacity": 5,
            "gradientMode": "none",
            "hideFrom": {
              "legend": false,
              "tooltip": false,
              "viz": false
            },
            "lineInterpolation": "smooth",
            "lineWidth": 2,
            "pointSize": 5,
            "scaleDistribution": {
              "type": "linear"
            },
            "showPoints": "auto",
            "spanNulls": false,
            "stacking": {
              "group": "A",
              "mode": "none"
            },
            "thresholdsStyle": {
              "mode": "off"
            }
          },
          "decimals": 3,
          "mappings": [],
          "thresholds": {
            "mode": "percentage",
            "steps": [
              {
                "color": "green",
                "value": null
              },
              {
                "color": "orange",
                "value": 80
              },
              {
                "color": "red",
                "value": 90
              }
            ]
          },
          "unit": "percent"
        },
        "overrides": []
      },
      "gridPos": {
        "h": 5,
        "w": 11,
        "x": 0,
        "y": 0
      },
      "id": 371,
      "options": {
        "legend": {
          "calcs": [],
          "displayMode": "hidden",
          "placement": "bottom"
        },
        "tooltip": {
          "mode": "single",
          "sort": "none"
        }
      },
      "pluginVersion": "9.0.5",
      "targets": [
        {
          "datasource": {
            "type": "prometheus",
            "uid": "${DATASOURCE}"
          },
          "editorMode": "code",
          "expr": "sum(node_namespace_pod_container:container_cpu_usage_seconds_total:sum_irate{namespace=\"arangodb\",pod=~\"$pod_cpu\"}) by (pod) / sum(cluster:namespace:pod_cpu:active:kube_pod_container_resource_limits{namespace=\"arangodb\",pod=~\"$pod_cpu\"}) by (pod)",
          "hide": true,
          "legendFormat": "{{pod}}",
          "range": true,
          "refId": "A"
        },
        {
          "datasource": {
            "type": "prometheus",
            "uid": "${DATASOURCE}"
          },
          "editorMode": "code",
          "expr": "sum(node_namespace_pod_container:container_cpu_usage_seconds_total:sum_irate{namespace=\"arangodb\",pod=~\"$pod_cpu\"}) by (pod) / sum(cluster:namespace:pod_cpu:active:kube_pod_container_resource_limits{namespace=\"arangodb\",pod=~\"$pod_cpu\"}) by (pod)",
          "hide": false,
          "legendFormat": "__auto",
          "range": true,
          "refId": "B"
        }
      ],
      "title": "CPU Utilisation (from limits)",
      "type": "timeseries"
    },
    {
      "datasource": {
        "type": "prometheus",
        "uid": "${DATASOURCE}"
      },
      "fieldConfig": {
        "defaults": {
          "color": {
            "mode": "thresholds"
          },
          "mappings": [
            {
              "options": {
                "null": {
                  "index": 0,
                  "text": "N/A"
                }
              },
              "type": "value"
            }
          ],
          "max": 100,
          "min": 0,
          "thresholds": {
            "mode": "absolute",
            "steps": [
              {
                "color": "green",
                "value": null
              },
              {
                "color": "orange",
                "value": 80
              },
              {
                "color": "red",
                "value": 90
              }
            ]
          },
          "unit": "percent"
        },
        "overrides": []
      },
      "gridPos": {
        "h": 5,
        "w": 3,
        "x": 11,
        "y": 0
      },
      "id": 369,
      "options": {
        "orientation": "horizontal",
        "reduceOptions": {
          "calcs": [
            "lastNotNull"
          ],
          "fields": "",
          "values": false
        },
        "showThresholdLabels": false,
        "showThresholdMarkers": true
      },
      "pluginVersion": "9.0.5",
      "targets": [
        {
          "datasource": {
            "type": "prometheus",
            "uid": "${DATASOURCE}"
          },
          "expr": "max without(instance,node) (\r\n(\r\n  topk(1, kubelet_volume_stats_capacity_bytes{job=\"kubelet\", metrics_path=\"/metrics\", namespace=\"arangodb\", persistentvolumeclaim=\"$volume\"})\r\n  -\r\n  topk(1, kubelet_volume_stats_available_bytes{job=\"kubelet\", metrics_path=\"/metrics\", namespace=\"arangodb\", persistentvolumeclaim=\"$volume\"})\r\n)\r\n/\r\ntopk(1, kubelet_volume_stats_capacity_bytes{job=\"kubelet\", metrics_path=\"/metrics\", namespace=\"arangodb\", persistentvolumeclaim=\"$volume\"})\r\n* 100)\r\n",
          "refId": "A"
        }
      ],
      "title": "Volume Space Usage",
      "type": "gauge"
    },
    {
      "datasource": {
        "type": "prometheus",
        "uid": "${DATASOURCE}"
      },
      "fieldConfig": {
        "defaults": {
          "color": {
            "mode": "thresholds"
          },
          "mappings": [],
          "thresholds": {
            "mode": "absolute",
            "steps": [
              {
                "color": "green",
                "value": null
              },
              {
                "color": "red",
                "value": 80
              }
            ]
          },
          "unit": "decgbytes"
        },
        "overrides": []
      },
      "gridPos": {
        "h": 5,
        "w": 5,
        "x": 14,
        "y": 0
      },
      "id": 347,
      "options": {
        "displayMode": "gradient",
        "minVizHeight": 10,
        "minVizWidth": 0,
        "orientation": "horizontal",
        "reduceOptions": {
          "calcs": [
            "lastNotNull"
          ],
          "fields": "",
          "values": false
        },
        "showUnfilled": true
      },
      "pluginVersion": "9.0.5",
      "targets": [
        {
          "datasource": {
            "type": "prometheus",
            "uid": "${DATASOURCE}"
          },
          "editorMode": "code",
          "exemplar": false,
          "expr": "arangodb_server_statistics_physical_memory{service=~\"$service\"} / (1024^3)",
          "instant": false,
          "legendFormat": "{{pod}}",
          "range": true,
          "refId": "A"
        }
      ],
      "title": "Выделенная физическая память",
      "type": "bargauge"
    },
    {
      "datasource": {
        "type": "prometheus",
        "uid": "${DATASOURCE}"
      },
      "fieldConfig": {
        "defaults": {
          "color": {
            "mode": "thresholds"
          },
          "mappings": [],
          "thresholds": {
            "mode": "percentage",
            "steps": [
              {
                "color": "green",
                "value": null
              }
            ]
          }
        },
        "overrides": []
      },
      "gridPos": {
        "h": 5,
        "w": 5,
        "x": 19,
        "y": 0
      },
      "id": 340,
      "options": {
        "displayMode": "gradient",
        "minVizHeight": 10,
        "minVizWidth": 0,
        "orientation": "horizontal",
        "reduceOptions": {
          "calcs": [
            "lastNotNull"
          ],
          "fields": "",
          "values": false
        },
        "showUnfilled": true
      },
      "pluginVersion": "9.0.5",
      "targets": [
        {
          "datasource": {
            "type": "prometheus",
            "uid": "${DATASOURCE}"
          },
          "editorMode": "code",
          "expr": "arangodb_server_statistics_cpu_cores{service=~\"$service\"}",
          "legendFormat": "{{pod}}",
          "range": true,
          "refId": "A"
        }
      ],
      "title": "Количество видимых ядер CPU",
      "type": "bargauge"
    },
    {
      "datasource": {
        "type": "prometheus",
        "uid": "${DATASOURCE}"
      },
      "fieldConfig": {
        "defaults": {
          "color": {
            "mode": "palette-classic"
          },
          "custom": {
            "axisLabel": "",
            "axisPlacement": "auto",
            "barAlignment": 0,
            "drawStyle": "line",
            "fillOpacity": 5,
            "gradientMode": "none",
            "hideFrom": {
              "legend": false,
              "tooltip": false,
              "viz": false
            },
            "lineInterpolation": "smooth",
            "lineWidth": 2,
            "pointSize": 1,
            "scaleDistribution": {
              "type": "linear"
            },
            "showPoints": "auto",
            "spanNulls": false,
            "stacking": {
              "group": "A",
              "mode": "none"
            },
            "thresholdsStyle": {
              "mode": "off"
            }
          },
          "mappings": [],
          "thresholds": {
            "mode": "percentage",
            "steps": [
              {
                "color": "green",
                "value": null
              }
            ]
          }
        },
        "overrides": []
      },
      "gridPos": {
        "h": 5,
        "w": 8,
        "x": 0,
        "y": 5
      },
      "id": 341,
      "options": {
        "legend": {
          "calcs": [],
          "displayMode": "hidden",
          "placement": "right"
        },
        "tooltip": {
          "mode": "single",
          "sort": "none"
        }
      },
      "pluginVersion": "9.0.5",
      "targets": [
        {
          "datasource": {
            "type": "prometheus",
            "uid": "${DATASOURCE}"
          },
          "editorMode": "code",
          "expr": "arangodb_server_statistics_idle_percent {service=~\"$service\"}",
          "legendFormat": "{{pod}}",
          "range": true,
          "refId": "A"
        }
      ],
      "title": "Процент времени, когда процессоры простаивали",
      "type": "timeseries"
    },
    {
      "datasource": {
        "type": "prometheus",
        "uid": "${DATASOURCE}"
      },
      "fieldConfig": {
        "defaults": {
          "color": {
            "mode": "palette-classic"
          },
          "custom": {
            "axisLabel": "",
            "axisPlacement": "auto",
            "barAlignment": 0,
            "drawStyle": "line",
            "fillOpacity": 5,
            "gradientMode": "none",
            "hideFrom": {
              "legend": false,
              "tooltip": false,
              "viz": false
            },
            "lineInterpolation": "smooth",
            "lineWidth": 2,
            "pointSize": 1,
            "scaleDistribution": {
              "type": "linear"
            },
            "showPoints": "auto",
            "spanNulls": false,
            "stacking": {
              "group": "A",
              "mode": "none"
            },
            "thresholdsStyle": {
              "mode": "off"
            }
          },
          "mappings": [],
          "thresholds": {
            "mode": "percentage",
            "steps": [
              {
                "color": "green",
                "value": null
              },
              {
                "color": "#EAB839",
                "value": 50
              },
              {
                "color": "red",
                "value": 80
              }
            ]
          }
        },
        "overrides": []
      },
      "gridPos": {
        "h": 5,
        "w": 8,
        "x": 8,
        "y": 5
      },
      "id": 342,
      "options": {
        "legend": {
          "calcs": [],
          "displayMode": "hidden",
          "placement": "right"
        },
        "tooltip": {
          "mode": "single",
          "sort": "none"
        }
      },
      "pluginVersion": "9.0.5",
      "targets": [
        {
          "datasource": {
            "type": "prometheus",
            "uid": "${DATASOURCE}"
          },
          "editorMode": "code",
          "expr": "arangodb_server_statistics_system_percent{service=~\"$service\"}",
          "legendFormat": "{{pod}}",
          "range": true,
          "refId": "A"
        }
      ],
      "title": "Процент времени, kernel-mode",
      "type": "timeseries"
    },
    {
      "datasource": {
        "type": "prometheus",
        "uid": "${DATASOURCE}"
      },
      "fieldConfig": {
        "defaults": {
          "color": {
            "mode": "palette-classic"
          },
          "custom": {
            "axisLabel": "",
            "axisPlacement": "auto",
            "barAlignment": 0,
            "drawStyle": "line",
            "fillOpacity": 5,
            "gradientMode": "none",
            "hideFrom": {
              "legend": false,
              "tooltip": false,
              "viz": false
            },
            "lineInterpolation": "smooth",
            "lineStyle": {
              "fill": "solid"
            },
            "lineWidth": 2,
            "pointSize": 1,
            "scaleDistribution": {
              "type": "linear"
            },
            "showPoints": "auto",
            "spanNulls": false,
            "stacking": {
              "group": "A",
              "mode": "none"
            },
            "thresholdsStyle": {
              "mode": "off"
            }
          },
          "mappings": [],
          "thresholds": {
            "mode": "percentage",
            "steps": [
              {
                "color": "green",
                "value": null
              }
            ]
          }
        },
        "overrides": []
      },
      "gridPos": {
        "h": 5,
        "w": 8,
        "x": 16,
        "y": 5
      },
      "id": 343,
      "options": {
        "legend": {
          "calcs": [],
          "displayMode": "hidden",
          "placement": "right"
        },
        "tooltip": {
          "mode": "single",
          "sort": "none"
        }
      },
      "pluginVersion": "9.0.5",
      "targets": [
        {
          "datasource": {
            "type": "prometheus",
            "uid": "${DATASOURCE}"
          },
          "editorMode": "code",
          "expr": "arangodb_server_statistics_user_percent {service=~\"$service\"}",
          "legendFormat": "{{pod}}",
          "range": true,
          "refId": "A"
        }
      ],
      "title": "Процент времени user-mode",
      "type": "timeseries"
    },
    {
      "datasource": {
        "type": "prometheus",
        "uid": "${DATASOURCE}"
      },
      "fieldConfig": {
        "defaults": {
          "color": {
            "mode": "palette-classic"
          },
          "custom": {
            "axisLabel": "",
            "axisPlacement": "auto",
            "barAlignment": 0,
            "drawStyle": "line",
            "fillOpacity": 5,
            "gradientMode": "opacity",
            "hideFrom": {
              "legend": false,
              "tooltip": false,
              "viz": false
            },
            "lineInterpolation": "smooth",
            "lineStyle": {
              "fill": "solid"
            },
            "lineWidth": 2,
            "pointSize": 1,
            "scaleDistribution": {
              "type": "linear"
            },
            "showPoints": "auto",
            "spanNulls": false,
            "stacking": {
              "group": "A",
              "mode": "none"
            },
            "thresholdsStyle": {
              "mode": "off"
            }
          },
          "mappings": [],
          "thresholds": {
            "mode": "absolute",
            "steps": [
              {
                "color": "green",
                "value": null
              },
              {
                "color": "red",
                "value": 80
              }
            ]
          },
          "unit": "decbytes"
        },
        "overrides": []
      },
      "gridPos": {
        "h": 5,
        "w": 8,
        "x": 0,
        "y": 10
      },
      "id": 351,
      "options": {
        "legend": {
          "calcs": [],
          "displayMode": "hidden",
          "placement": "right"
        },
        "tooltip": {
          "mode": "single",
          "sort": "none"
        }
      },
      "pluginVersion": "9.0.5",
      "targets": [
        {
          "datasource": {
            "type": "prometheus",
            "uid": "${DATASOURCE}"
          },
          "editorMode": "code",
          "expr": "arangodb_process_statistics_virtual_memory_size{service=~\"$service\"} ",
          "legendFormat": "{{pod}}",
          "range": true,
          "refId": "A"
        }
      ],
      "title": "Размер виртуальной памяти, используемой процессом",
      "type": "timeseries"
    },
    {
      "datasource": {
        "type": "prometheus",
        "uid": "${DATASOURCE}"
      },
      "fieldConfig": {
        "defaults": {
          "color": {
            "mode": "palette-classic"
          },
          "custom": {
            "axisLabel": "",
            "axisPlacement": "auto",
            "barAlignment": 0,
            "drawStyle": "line",
            "fillOpacity": 5,
            "gradientMode": "opacity",
            "hideFrom": {
              "legend": false,
              "tooltip": false,
              "viz": false
            },
            "lineInterpolation": "smooth",
            "lineStyle": {
              "fill": "solid"
            },
            "lineWidth": 2,
            "pointSize": 1,
            "scaleDistribution": {
              "type": "linear"
            },
            "showPoints": "auto",
            "spanNulls": false,
            "stacking": {
              "group": "A",
              "mode": "none"
            },
            "thresholdsStyle": {
              "mode": "off"
            }
          },
          "mappings": [],
          "thresholds": {
            "mode": "absolute",
            "steps": [
              {
                "color": "green",
                "value": null
              },
              {
                "color": "red",
                "value": 80
              }
            ]
          },
          "unit": "none"
        },
        "overrides": []
      },
      "gridPos": {
        "h": 5,
        "w": 8,
        "x": 8,
        "y": 10
      },
      "id": 353,
      "options": {
        "legend": {
          "calcs": [],
          "displayMode": "hidden",
          "placement": "right"
        },
        "tooltip": {
          "mode": "single",
          "sort": "none"
        }
      },
      "pluginVersion": "9.0.5",
      "targets": [
        {
          "datasource": {
            "type": "prometheus",
            "uid": "${DATASOURCE}"
          },
          "editorMode": "code",
          "expr": "rate(arangodb_process_statistics_major_page_faults_total{service=~\"$service\"}[$__rate_interval])",
          "legendFormat": "{{pod}}",
          "range": true,
          "refId": "A"
        }
      ],
      "title": "Число значительных отказов страниц (показатель может сопровождать замедление работы системы)",
      "type": "timeseries"
    },
    {
      "datasource": {
        "type": "prometheus",
        "uid": "${DATASOURCE}"
      },
      "fieldConfig": {
        "defaults": {
          "color": {
            "mode": "palette-classic"
          },
          "custom": {
            "axisLabel": "",
            "axisPlacement": "auto",
            "barAlignment": 0,
            "drawStyle": "line",
            "fillOpacity": 5,
            "gradientMode": "opacity",
            "hideFrom": {
              "legend": false,
              "tooltip": false,
              "viz": false
            },
            "lineInterpolation": "smooth",
            "lineStyle": {
              "fill": "solid"
            },
            "lineWidth": 2,
            "pointSize": 1,
            "scaleDistribution": {
              "type": "linear"
            },
            "showPoints": "auto",
            "spanNulls": false,
            "stacking": {
              "group": "A",
              "mode": "none"
            },
            "thresholdsStyle": {
              "mode": "off"
            }
          },
          "mappings": [],
          "thresholds": {
            "mode": "absolute",
            "steps": [
              {
                "color": "green",
                "value": null
              },
              {
                "color": "red",
                "value": 80
              }
            ]
          },
          "unit": "percent"
        },
        "overrides": []
      },
      "gridPos": {
        "h": 5,
        "w": 8,
        "x": 16,
        "y": 10
      },
      "id": 352,
      "options": {
        "legend": {
          "calcs": [],
          "displayMode": "hidden",
          "placement": "right"
        },
        "tooltip": {
          "mode": "single",
          "sort": "none"
        }
      },
      "pluginVersion": "9.0.5",
      "targets": [
        {
          "datasource": {
            "type": "prometheus",
            "uid": "${DATASOURCE}"
          },
          "editorMode": "code",
          "expr": "arangodb_process_statistics_resident_set_size_percent {service=~\"$service\"} ",
          "legendFormat": "{{pod}}",
          "range": true,
          "refId": "A"
        }
      ],
      "title": "Относительный размер количества страниц, которые процесс имеет в реальной памяти по сравнению с системной памятью",
      "type": "timeseries"
    },
    {
      "datasource": {
        "type": "prometheus",
        "uid": "${DATASOURCE}"
      },
      "description": "Количество клиентских подключений, открытых в данный момент (только соединения HTTP и HTTP/2, но не соединения VST)",
      "fieldConfig": {
        "defaults": {
          "color": {
            "mode": "palette-classic"
          },
          "custom": {
            "axisLabel": "",
            "axisPlacement": "auto",
            "barAlignment": 0,
            "drawStyle": "line",
            "fillOpacity": 5,
            "gradientMode": "none",
            "hideFrom": {
              "legend": false,
              "tooltip": false,
              "viz": false
            },
            "lineInterpolation": "smooth",
            "lineWidth": 2,
            "pointSize": 1,
            "scaleDistribution": {
              "type": "linear"
            },
            "showPoints": "auto",
            "spanNulls": false,
            "stacking": {
              "group": "A",
              "mode": "none"
            },
            "thresholdsStyle": {
              "mode": "off"
            }
          },
          "mappings": [],
          "thresholds": {
            "mode": "absolute",
            "steps": [
              {
                "color": "green",
                "value": null
              },
              {
                "color": "red",
                "value": 80
              }
            ]
          }
        },
        "overrides": []
      },
      "gridPos": {
        "h": 5,
        "w": 8,
        "x": 0,
        "y": 15
      },
      "id": 357,
      "options": {
        "legend": {
          "calcs": [],
          "displayMode": "hidden",
          "placement": "right"
        },
        "tooltip": {
          "mode": "single",
          "sort": "none"
        }
      },
      "targets": [
        {
          "datasource": {
            "type": "prometheus",
            "uid": "${DATASOURCE}"
          },
          "editorMode": "code",
          "expr": "arangodb_client_connection_statistics_client_connections{service=~\"$service\"}",
          "legendFormat": "{{pod}}",
          "range": true,
          "refId": "A"
        }
      ],
      "title": "Количество подключений",
      "type": "timeseries"
    },
    {
      "datasource": {
        "type": "prometheus",
        "uid": "${DATASOURCE}"
      },
      "description": "Время между моментом установления соединения и моментом его закрытия (меньшие числа указывают на то, что нагрузка невелика)",
      "fieldConfig": {
        "defaults": {
          "color": {
            "mode": "palette-classic"
          },
          "custom": {
            "axisLabel": "",
            "axisPlacement": "auto",
            "barAlignment": 0,
            "drawStyle": "line",
            "fillOpacity": 5,
            "gradientMode": "none",
            "hideFrom": {
              "legend": false,
              "tooltip": false,
              "viz": false
            },
            "lineInterpolation": "smooth",
            "lineWidth": 2,
            "pointSize": 1,
            "scaleDistribution": {
              "type": "linear"
            },
            "showPoints": "auto",
            "spanNulls": false,
            "stacking": {
              "group": "A",
              "mode": "none"
            },
            "thresholdsStyle": {
              "mode": "off"
            }
          },
          "mappings": [],
          "thresholds": {
            "mode": "absolute",
            "steps": [
              {
                "color": "green",
                "value": null
              },
              {
                "color": "red",
                "value": 80
              }
            ]
          }
        },
        "overrides": []
      },
      "gridPos": {
        "h": 5,
        "w": 8,
        "x": 8,
        "y": 15
      },
      "id": 358,
      "options": {
        "legend": {
          "calcs": [],
          "displayMode": "hidden",
          "placement": "right"
        },
        "tooltip": {
          "mode": "single",
          "sort": "none"
        }
      },
      "targets": [
        {
          "datasource": {
            "type": "prometheus",
            "uid": "${DATASOURCE}"
          },
          "editorMode": "code",
          "expr": "rate(arangodb_client_connection_statistics_connection_time_count {service=~\"$service\"}[$__rate_interval])",
          "legendFormat": "{{pod}}",
          "range": true,
          "refId": "A"
        }
      ],
      "title": "Время жизни соединения(count/sec)",
      "type": "timeseries"
    },
    {
      "datasource": {
        "type": "prometheus",
        "uid": "${DATASOURCE}"
      },
      "description": "Время, необходимое для ответа на запрос",
      "fieldConfig": {
        "defaults": {
          "color": {
            "mode": "palette-classic"
          },
          "custom": {
            "axisLabel": "",
            "axisPlacement": "auto",
            "barAlignment": 0,
            "drawStyle": "line",
            "fillOpacity": 5,
            "gradientMode": "none",
            "hideFrom": {
              "legend": false,
              "tooltip": false,
              "viz": false
            },
            "lineInterpolation": "smooth",
            "lineWidth": 2,
            "pointSize": 1,
            "scaleDistribution": {
              "type": "linear"
            },
            "showPoints": "auto",
            "spanNulls": false,
            "stacking": {
              "group": "A",
              "mode": "none"
            },
            "thresholdsStyle": {
              "mode": "off"
            }
          },
          "mappings": [],
          "thresholds": {
            "mode": "absolute",
            "steps": [
              {
                "color": "green",
                "value": null
              },
              {
                "color": "red",
                "value": 80
              }
            ]
          }
        },
        "overrides": []
      },
      "gridPos": {
        "h": 5,
        "w": 8,
        "x": 16,
        "y": 15
      },
      "id": 359,
      "options": {
        "legend": {
          "calcs": [],
          "displayMode": "hidden",
          "placement": "right"
        },
        "tooltip": {
          "mode": "single",
          "sort": "none"
        }
      },
      "targets": [
        {
          "datasource": {
            "type": "prometheus",
            "uid": "${DATASOURCE}"
          },
          "editorMode": "code",
          "expr": "rate(arangodb_client_connection_statistics_io_time_sum{service=~\"$service\"}[$__rate_interval]) / rate(arangodb_client_connection_statistics_io_time_count{service=~\"$service\"}[$__rate_interval])",
          "legendFormat": "{{pod}}",
          "range": true,
          "refId": "A"
        }
      ],
      "title": "I/O time необходимое для ответа на запрос (avg per sec)",
      "type": "timeseries"
    },
    {
      "datasource": {
        "type": "prometheus",
        "uid": "${DATASOURCE}"
      },
      "description": "Общее количество HTTP-запросов в разбивке по методам",
      "fieldConfig": {
        "defaults": {
          "color": {
            "mode": "palette-classic"
          },
          "custom": {
            "axisLabel": "",
            "axisPlacement": "auto",
            "barAlignment": 0,
            "drawStyle": "line",
            "fillOpacity": 5,
            "gradientMode": "none",
            "hideFrom": {
              "legend": false,
              "tooltip": false,
              "viz": false
            },
            "lineInterpolation": "smooth",
            "lineWidth": 2,
            "pointSize": 1,
            "scaleDistribution": {
              "type": "linear"
            },
            "showPoints": "auto",
            "spanNulls": false,
            "stacking": {
              "group": "A",
              "mode": "none"
            },
            "thresholdsStyle": {
              "mode": "off"
            }
          },
          "mappings": [],
          "thresholds": {
            "mode": "absolute",
            "steps": [
              {
                "color": "green",
                "value": null
              },
              {
                "color": "red",
                "value": 80
              }
            ]
          }
        },
        "overrides": []
      },
      "gridPos": {
        "h": 5,
        "w": 8,
        "x": 0,
        "y": 20
      },
      "id": 361,
      "options": {
        "legend": {
          "calcs": [],
          "displayMode": "hidden",
          "placement": "right"
        },
        "tooltip": {
          "mode": "single",
          "sort": "none"
        }
      },
      "targets": [
        {
          "datasource": {
            "type": "prometheus",
            "uid": "${DATASOURCE}"
          },
          "editorMode": "code",
          "expr": "rate(arangodb_http_request_statistics_http_get_requests_total{service=~\"$service\"}[$__rate_interval])",
          "hide": false,
          "legendFormat": "GET:{{pod}}",
          "range": true,
          "refId": "A"
        },
        {
          "datasource": {
            "type": "prometheus",
            "uid": "${DATASOURCE}"
          },
          "editorMode": "code",
          "expr": "rate(arangodb_http_request_statistics_http_post_requests_total{service=~\"$service\"}[$__rate_interval])",
          "hide": false,
          "legendFormat": "POST:{{pod}}",
          "range": true,
          "refId": "B"
        },
        {
          "datasource": {
            "type": "prometheus",
            "uid": "${DATASOURCE}"
          },
          "editorMode": "code",
          "expr": "rate(arangodb_http_request_statistics_http_put_requests_total{service=~\"$service\"}[$__rate_interval])",
          "hide": false,
          "legendFormat": "PUT:{{pod}}",
          "range": true,
          "refId": "C"
        },
        {
          "datasource": {
            "type": "prometheus",
            "uid": "${DATASOURCE}"
          },
          "editorMode": "code",
          "expr": "rate(arangodb_http_request_statistics_http_delete_requests_total{service=~\"$service\"}[$__rate_interval])",
          "hide": false,
          "legendFormat": "DELETE:{{pod}}",
          "range": true,
          "refId": "D"
        },
        {
          "datasource": {
            "type": "prometheus",
            "uid": "${DATASOURCE}"
          },
          "editorMode": "code",
          "expr": "rate(arangodb_http_request_statistics_http_options_requests_total{service=~\"$service\"}[$__rate_interval])",
          "hide": true,
          "legendFormat": "OPTIONS:{{pod}}",
          "range": true,
          "refId": "E"
        },
        {
          "datasource": {
            "type": "prometheus",
            "uid": "${DATASOURCE}"
          },
          "editorMode": "code",
          "expr": "rate(arangodb_http_request_statistics_http_patch_requests_total{service=~\"$service\"}[$__rate_interval])",
          "hide": false,
          "legendFormat": "PATCH:{{pod}}",
          "range": true,
          "refId": "F"
        },
        {
          "datasource": {
            "type": "prometheus",
            "uid": "${DATASOURCE}"
          },
          "editorMode": "code",
          "expr": "rate(arangodb_http_request_statistics_http_head_requests_total{service=~\"$service\"}[$__rate_interval])",
          "hide": true,
          "legendFormat": "HEAD:{{pod}}",
          "range": true,
          "refId": "G"
        }
      ],
      "title": "Количество запросов HTTP(по методам)",
      "type": "timeseries"
    },
    {
      "datasource": {
        "type": "prometheus",
        "uid": "${DATASOURCE}"
      },
      "description": "Общее количество HTTP-запросов",
      "fieldConfig": {
        "defaults": {
          "color": {
            "mode": "palette-classic"
          },
          "custom": {
            "axisLabel": "",
            "axisPlacement": "auto",
            "barAlignment": 0,
            "drawStyle": "line",
            "fillOpacity": 5,
            "gradientMode": "none",
            "hideFrom": {
              "legend": false,
              "tooltip": false,
              "viz": false
            },
            "lineInterpolation": "smooth",
            "lineWidth": 2,
            "pointSize": 1,
            "scaleDistribution": {
              "type": "linear"
            },
            "showPoints": "auto",
            "spanNulls": false,
            "stacking": {
              "group": "A",
              "mode": "none"
            },
            "thresholdsStyle": {
              "mode": "off"
            }
          },
          "mappings": [],
          "thresholds": {
            "mode": "absolute",
            "steps": [
              {
                "color": "green",
                "value": null
              },
              {
                "color": "red",
                "value": 80
              }
            ]
          }
        },
        "overrides": []
      },
      "gridPos": {
        "h": 5,
        "w": 8,
        "x": 8,
        "y": 20
      },
      "id": 360,
      "options": {
        "legend": {
          "calcs": [],
          "displayMode": "hidden",
          "placement": "right"
        },
        "tooltip": {
          "mode": "single",
          "sort": "none"
        }
      },
      "targets": [
        {
          "datasource": {
            "type": "prometheus",
            "uid": "${DATASOURCE}"
          },
          "editorMode": "code",
          "expr": "rate(arangodb_http_request_statistics_total_requests_total{service=~\"$service\"}[$__rate_interval])",
          "legendFormat": "{{pod}}",
          "range": true,
          "refId": "A"
        }
      ],
      "title": "Количество запросов HTTP",
      "type": "timeseries"
    },
    {
      "datasource": {
        "type": "prometheus",
        "uid": "${DATASOURCE}"
      },
      "description": "",
      "fieldConfig": {
        "defaults": {
          "color": {
            "mode": "palette-classic"
          },
          "custom": {
            "axisLabel": "",
            "axisPlacement": "auto",
            "barAlignment": 0,
            "drawStyle": "line",
            "fillOpacity": 5,
            "gradientMode": "none",
            "hideFrom": {
              "legend": false,
              "tooltip": false,
              "viz": false
            },
            "lineInterpolation": "smooth",
            "lineWidth": 2,
            "pointSize": 1,
            "scaleDistribution": {
              "type": "linear"
            },
            "showPoints": "auto",
            "spanNulls": false,
            "stacking": {
              "group": "A",
              "mode": "none"
            },
            "thresholdsStyle": {
              "mode": "off"
            }
          },
          "mappings": [],
          "thresholds": {
            "mode": "absolute",
            "steps": [
              {
                "color": "green",
                "value": null
              },
              {
                "color": "red",
                "value": 80
              }
            ]
          }
        },
        "overrides": []
      },
      "gridPos": {
        "h": 5,
        "w": 8,
        "x": 16,
        "y": 20
      },
      "id": 363,
      "options": {
        "legend": {
          "calcs": [],
          "displayMode": "hidden",
          "placement": "right"
        },
        "tooltip": {
          "mode": "single",
          "sort": "none"
        }
      },
      "targets": [
        {
          "datasource": {
            "type": "prometheus",
            "uid": "${DATASOURCE}"
          },
          "editorMode": "code",
          "expr": "arangodb_process_statistics_number_of_threads{service=~\"$service\"}",
          "hide": false,
          "legendFormat": "{{pod}}",
          "range": true,
          "refId": "A"
        }
      ],
      "title": "Число потоков",
      "type": "timeseries"
    },
    {
      "datasource": {
        "type": "prometheus",
        "uid": "${DATASOURCE}"
      },
      "description": "Предупреждения системы  (не всегда свидетельствуют о ошибках, но порой интересные, например, насколько понимаю, среди них встречаются уведомления о медленных запросах)including startup warnings.\n\n",
      "fieldConfig": {
        "defaults": {
          "color": {
            "mode": "palette-classic"
          },
          "custom": {
            "axisLabel": "",
            "axisPlacement": "auto",
            "barAlignment": 0,
            "drawStyle": "line",
            "fillOpacity": 5,
            "gradientMode": "none",
            "hideFrom": {
              "legend": false,
              "tooltip": false,
              "viz": false
            },
            "lineInterpolation": "smooth",
            "lineStyle": {
              "fill": "solid"
            },
            "lineWidth": 2,
            "pointSize": 5,
            "scaleDistribution": {
              "type": "linear"
            },
            "showPoints": "never",
            "spanNulls": false,
            "stacking": {
              "group": "A",
              "mode": "none"
            },
            "thresholdsStyle": {
              "mode": "off"
            }
          },
          "mappings": [],
          "thresholds": {
            "mode": "absolute",
            "steps": [
              {
                "color": "green"
              },
              {
                "color": "red",
                "value": 80
              }
            ]
          },
          "unit": "short"
        },
        "overrides": []
      },
      "gridPos": {
        "h": 5,
        "w": 8,
        "x": 0,
        "y": 25
      },
      "id": 167,
      "options": {
        "legend": {
          "calcs": [],
          "displayMode": "hidden",
          "placement": "right"
        },
        "tooltip": {
          "mode": "multi",
          "sort": "none"
        }
      },
      "pluginVersion": "9.0.5",
      "targets": [
        {
          "datasource": {
            "type": "prometheus",
            "uid": "${DATASOURCE}"
          },
          "exemplar": true,
          "expr": "rate(arangodb_logger_warnings_total{service=~\"$service\"}[3m])",
          "interval": "",
          "legendFormat": "{{pod}}:{{shortname}}",
          "refId": "A"
        }
      ],
      "title": "Общее количество предупреждений",
      "type": "timeseries"
    },
    {
      "cards": {},
      "color": {
        "cardColor": "#b4ff00",
        "colorScale": "sqrt",
        "colorScheme": "interpolateOranges",
        "exponent": 0.5,
        "mode": "spectrum"
      },
      "dataFormat": "timeseries",
      "datasource": {
        "type": "prometheus",
        "uid": "${DATASOURCE}"
      },
      "description": "",
      "gridPos": {
        "h": 5,
        "w": 8,
        "x": 8,
        "y": 25
      },
      "heatmap": {},
      "hideZeroBuckets": false,
      "highlightCards": true,
      "id": 362,
      "legend": {
        "show": false
      },
      "pluginVersion": "9.0.5",
      "reverseYBuckets": false,
      "targets": [
        {
          "datasource": {
            "type": "prometheus",
            "uid": "${DATASOURCE}"
          },
          "editorMode": "code",
          "exemplar": true,
          "expr": "histogram_quantile(0.95, sum(rate(arangodb_request_body_size_vst_bucket{service=~\"$service\"}[$__rate_interval])) by (le))",
          "interval": "",
          "legendFormat": "{{pod}}",
          "range": true,
          "refId": "A"
        }
      ],
      "title": "Размер тела полученных VST-запросов",
      "tooltip": {
        "show": true,
        "showHistogram": false
      },
      "type": "heatmap",
      "xAxis": {
        "show": true
      },
      "yAxis": {
        "format": "short",
        "logBase": 1,
        "show": true
      },
      "yBucketBound": "auto"
    },
    {
      "datasource": {
        "type": "prometheus",
        "uid": "${DATASOURCE}"
      },
      "description": "Ошибки фатальные для какой-либо операции, но не для службы/сервиса в целом\n",
      "fieldConfig": {
        "defaults": {
          "color": {
            "mode": "palette-classic"
          },
          "custom": {
            "axisLabel": "",
            "axisPlacement": "auto",
            "barAlignment": 0,
            "drawStyle": "line",
            "fillOpacity": 5,
            "gradientMode": "none",
            "hideFrom": {
              "legend": false,
              "tooltip": false,
              "viz": false
            },
            "lineInterpolation": "smooth",
            "lineWidth": 2,
            "pointSize": 5,
            "scaleDistribution": {
              "type": "linear"
            },
            "showPoints": "never",
            "spanNulls": false,
            "stacking": {
              "group": "A",
              "mode": "none"
            },
            "thresholdsStyle": {
              "mode": "off"
            }
          },
          "mappings": [],
          "thresholds": {
            "mode": "absolute",
            "steps": [
              {
                "color": "green"
              },
              {
                "color": "red",
                "value": 80
              }
            ]
          },
          "unit": "short"
        },
        "overrides": []
      },
      "gridPos": {
        "h": 5,
        "w": 8,
        "x": 16,
        "y": 25
      },
      "id": 166,
      "options": {
        "legend": {
          "calcs": [],
          "displayMode": "hidden",
          "placement": "right"
        },
        "tooltip": {
          "mode": "multi",
          "sort": "none"
        }
      },
      "pluginVersion": "9.0.5",
      "targets": [
        {
          "datasource": {
            "type": "prometheus",
            "uid": "${DATASOURCE}"
          },
          "exemplar": true,
          "expr": "rate(arangodb_logger_errors_total{service=~\"$service\"}[$__rate_interval])",
          "interval": "",
          "legendFormat": "{{pod}}:{{shortname}}",
          "refId": "A"
        }
      ],
      "title": "Общее количество ошибок",
      "type": "timeseries"
    }
  ],
  "refresh": false,
  "schemaVersion": 36,
  "style": "dark",
  "tags": [],
  "templating": {
    "list": [
      {
        "current": {
          "selected": false,
          "text": "Prometheus-NT",
          "value": "Prometheus-NT"
        },
        "hide": 0,
        "includeAll": false,
        "label": "DATASOURCE",
        "multi": false,
        "name": "DATASOURCE",
        "options": [],
        "query": "prometheus",
        "queryValue": "",
        "refresh": 1,
        "regex": "Prometheus-NT",
        "skipUrlSync": false,
        "type": "datasource"
      },
      {
        "allValue": ".*",
        "current": {
          "selected": true,
          "text": [
            "All"
          ],
          "value": [
            "$__all"
          ]
        },
        "datasource": {
          "type": "prometheus",
          "uid": "${DATASOURCE}"
        },
        "definition": "query_result(arangodb_connection_pool_connections_created_total{service=~\"$service\", namespace=\"arangodb\"})",
        "hide": 0,
        "includeAll": true,
        "label": "Service",
        "multi": false,
        "name": "service",
        "options": [],
        "query": {
          "query": "query_result(arangodb_connection_pool_connections_created_total{service=~\"$service\", namespace=\"arangodb\"})",
          "refId": "StandardVariableQuery"
        },
        "refresh": 1,
        "regex": "/.*service=\"([^\"]*).*/",
        "skipUrlSync": false,
        "sort": 0,
        "type": "query"
      },
      {
        "allValue": ".*",
        "current": {
          "selected": false,
          "text": "apps-address-registry-arango-single-pc8yar8i",
          "value": "apps-address-registry-arango-single-pc8yar8i"
        },
        "datasource": {
          "type": "prometheus",
          "uid": "${DATASOURCE}"
        },
        "definition": "label_values(kubelet_volume_stats_capacity_bytes{job=\"kubelet\", metrics_path=\"/metrics\", namespace=\"arangodb\"}, persistentvolumeclaim)",
        "hide": 0,
        "includeAll": false,
        "label": "DiskVolume",
        "multi": false,
        "name": "volume",
        "options": [],
        "query": {
          "query": "label_values(kubelet_volume_stats_capacity_bytes{job=\"kubelet\", metrics_path=\"/metrics\", namespace=\"arangodb\"}, persistentvolumeclaim)",
          "refId": "StandardVariableQuery"
        },
        "refresh": 2,
        "regex": "",
        "skipUrlSync": false,
        "sort": 1,
        "type": "query"
      },
      {
        "allValue": ".*",
        "current": {
          "selected": false,
          "text": "All",
          "value": "$__all"
        },
        "datasource": {
          "type": "prometheus",
          "uid": "${DATASOURCE}"
        },
        "definition": "node_namespace_pod_container:container_cpu_usage_seconds_total:sum_irate{namespace=\"arangodb\"}",
        "hide": 0,
        "includeAll": true,
        "label": "Pod(CPU)",
        "multi": false,
        "name": "pod_cpu",
        "options": [],
        "query": {
          "query": "node_namespace_pod_container:container_cpu_usage_seconds_total:sum_irate{namespace=\"arangodb\"}",
          "refId": "StandardVariableQuery"
        },
        "refresh": 1,
        "regex": "/.*pod=\"([^\"]*).*/",
        "skipUrlSync": false,
        "sort": 0,
        "type": "query"
      }
    ]
  },
  "time": {
    "from": "2023-12-07T19:25:56.986Z",
    "to": "2023-12-08T21:23:11.300Z"
  },
  "timepicker": {
    "hidden": false
  },
  "timezone": "",
  "title": "[PROD] ArangoDB 3.9 mini",
  "uid": "TFHfBRdSk",
  "version": 7,
  "weekStart": ""
}